drf_spectacular_sidecar/__init__.py
drf_spectacular_sidecar/apps.py
drf_spectacular_sidecar/py.typed
drf_spectacular_sidecar/static/drf_spectacular_sidecar/redoc/bundles/redoc.standalone.js
drf_spectacular_sidecar/static/drf_spectacular_sidecar/redoc/bundles/redoc.standalone.js.LICENSE.txt
drf_spectacular_sidecar/static/drf_spectacular_sidecar/redoc/bundles/redoc.standalone.js.map
drf_spectacular_sidecar/static/drf_spectacular_sidecar/swagger-ui-dist/favicon-32x32.png
drf_spectacular_sidecar/static/drf_spectacular_sidecar/swagger-ui-dist/oauth2-redirect.html
drf_spectacular_sidecar/static/drf_spectacular_sidecar/swagger-ui-dist/swagger-ui-bundle.js
drf_spectacular_sidecar/static/drf_spectacular_sidecar/swagger-ui-dist/swagger-ui-bundle.js.LICENSE.txt
drf_spectacular_sidecar/static/drf_spectacular_sidecar/swagger-ui-dist/swagger-ui-bundle.js.map
drf_spectacular_sidecar/static/drf_spectacular_sidecar/swagger-ui-dist/swagger-ui-standalone-preset.js
drf_spectacular_sidecar/static/drf_spectacular_sidecar/swagger-ui-dist/swagger-ui-standalone-preset.js.map
drf_spectacular_sidecar/static/drf_spectacular_sidecar/swagger-ui-dist/swagger-ui.css
drf_spectacular_sidecar/static/drf_spectacular_sidecar/swagger-ui-dist/swagger-ui.css.map
drf_spectacular_sidecar-2024.7.1.dist-info/LICENSE
drf_spectacular_sidecar-2024.7.1.dist-info/METADATA
drf_spectacular_sidecar-2024.7.1.dist-info/WHEEL
drf_spectacular_sidecar-2024.7.1.dist-info/top_level.txt
drf_spectacular_sidecar-2024.7.1.dist-info/RECORD
