Metadata-Version: 2.1
Name: drf-spectacular-sidecar
Version: 2024.7.1
Summary: Serve self-contained distribution builds of Swagger UI and Redoc with Django
Home-page: https://github.com/tfranzel/drf-spectacular-sidecar
Author: T. Franzel
Author-email: tfranzel@gmail.com
License: BSD
Project-URL: Source, https://github.com/tfranzel/drf-spectacular-sidecar
Project-URL: Documentation, https://drf-spectacular.readthedocs.io
Classifier: Development Status :: 5 - Production/Stable
Classifier: Environment :: Web Environment
Classifier: Framework :: Django
Classifier: Intended Audience :: Developers
Classifier: License :: OSI Approved :: BSD License
Classifier: Operating System :: OS Independent
Classifier: Natural Language :: English
Classifier: Programming Language :: Python :: 3
Classifier: Topic :: Internet :: WWW/HTTP
Classifier: Topic :: Documentation
Classifier: Topic :: Software Development :: Code Generators
Requires-Python: >=3.6
License-File: LICENSE
Requires-Dist: Django>=2.2
